README.md
setup.py
FPL_wildcard_team_selector/__init__.py
FPL_wildcard_team_selector/initiate_team_selection_pipeline.py
FPL_wildcard_team_selector.egg-info/PKG-INFO
FPL_wildcard_team_selector.egg-info/SOURCES.txt
FPL_wildcard_team_selector.egg-info/dependency_links.txt
FPL_wildcard_team_selector.egg-info/requires.txt
FPL_wildcard_team_selector.egg-info/top_level.txt
FPL_wildcard_team_selector/FPL_data_collection/__init__.py
FPL_wildcard_team_selector/FPL_data_collection/constants.py
FPL_wildcard_team_selector/FPL_data_collection/data_loader_fpl_api.py
FPL_wildcard_team_selector/FPL_data_collection/data_loader_understat_url.py
FPL_wildcard_team_selector/FPL_data_collection/utilities.py
FPL_wildcard_team_selector/FPL_data_processing/__init__.py
FPL_wildcard_team_selector/FPL_data_processing/player_metrics.py
FPL_wildcard_team_selector/FPL_data_processing/player_rating_generator.py
FPL_wildcard_team_selector/FPL_data_processing/team_selection.py
FPL_wildcard_team_selector/FPL_data_processing/utilities.py
FPL_wildcard_team_selector/FPL_data_visualization/__init__.py
FPL_wildcard_team_selector/FPL_data_visualization/team_selection_visualization.py