Metadata-Version: 2.1
Name: FPL-wildcard-team-selector
Version: 1.1.1
Summary: This package helps you select the best 15 players to choose when playing a wildcard on Fantasy premier league on any given week
Home-page: https://github.com/abdul-gendy/FPL_wildcard_team_selector
Author: Abdulrahman Elgendy
Author-email: Abdul.Elgendy@outlook.com
License: UNKNOWN
Download-URL: https://github.com/abdul-gendy/FPL_wildcard_team_selector/archive/v1.1.1.tar.gz
Platform: UNKNOWN
Classifier: Programming Language :: Python :: 3
Classifier: License :: OSI Approved :: MIT License
Classifier: Operating System :: OS Independent
Requires-Python: >=3.6
